v3cap/__init__.py
v3cap/__main__.py
v3cap/api.py
v3cap/captcha.py
v3cap/version.py
v3cap-0.0.3.dist-info/licenses/LICENSE
v3cap-0.0.3.dist-info/METADATA
v3cap-0.0.3.dist-info/WHEEL
v3cap-0.0.3.dist-info/entry_points.txt
v3cap-0.0.3.dist-info/top_level.txt
v3cap-0.0.3.dist-info/RECORD
