Metadata-Version: 2.4
Name: v3cap
Version: 0.0.3
Summary: reCAPTCHA v3 solver package
Author-email: TanmoyTheBoT <tanmoysarkershuvo@gmail.com>
License: MIT
Project-URL: Homepage, https://github.com/TanmoyTheBoT/v3cap
Project-URL: Issues, https://github.com/TanmoyTheBoT/v3cap/issues
Classifier: Programming Language :: Python :: 3
Classifier: License :: OSI Approved :: MIT License
Classifier: Operating System :: OS Independent
Requires-Python: >=3.10
License-File: LICENSE
Requires-Dist: fastapi>=0.115.12
Requires-Dist: requests>=2.32.3
Requires-Dist: seleniumbase>=4.38.3
Requires-Dist: uvicorn>=0.34.2
Dynamic: license-file
